name_sdk/__init__.py
name_sdk/name_combiner.py
simple_name_sdk-0.2.0.dist-info/METADATA
simple_name_sdk-0.2.0.dist-info/WHEEL
simple_name_sdk-0.2.0.dist-info/top_level.txt
simple_name_sdk-0.2.0.dist-info/RECORD
